beautifurl/__init__.py
beautifurl/beautifurl.py
beautifurl/test_beautifurl.py
beautifurl/dictionaries/A_animals
beautifurl/dictionaries/a_adjectives
beautifurl/dictionaries/organise.py
beautifurl-0.1.4.dist-info/LICENSE
beautifurl-0.1.4.dist-info/METADATA
beautifurl-0.1.4.dist-info/WHEEL
beautifurl-0.1.4.dist-info/top_level.txt
beautifurl-0.1.4.dist-info/RECORD
