Metadata-Version: 2.1
Name: beautifurl
Version: 0.1.4
Summary: Generates beautiful urls similar to Gfycat.
Home-page: https://github.com/hintofbasil/Python-Beautifurl
Author: William Hutcheson
Author-email: crabbybearnose@shadowmail.co.uk
License: MIT
Platform: UNKNOWN
Classifier: Development Status :: 4 - Beta
Classifier: License :: OSI Approved :: MIT License
Classifier: Environment :: Web Environment
Classifier: Intended Audience :: Developers
Classifier: Operating System :: OS Independent
Classifier: Programming Language :: Python
Classifier: Topic :: Internet :: WWW/HTTP
Classifier: Programming Language :: Python :: 2
Classifier: Programming Language :: Python :: 3
Requires-Dist: shuffled (>=0.2)
